meyicloud_pw_ui_utils/__init__.py
meyicloud_pw_ui_utils/actions/__init__.py
meyicloud_pw_ui_utils/actions/clicks.py
meyicloud_pw_ui_utils/actions/inputs.py
meyicloud_pw_ui_utils/assertions/__init__.py
meyicloud_pw_ui_utils/assertions/assertions.py
meyicloud_pw_ui_utils/dropdowns/__init__.py
meyicloud_pw_ui_utils/dropdowns/dropdowns.py
meyicloud_pw_ui_utils/locators/__init__.py
meyicloud_pw_ui_utils/locators/locators.py
meyicloud_pw_ui_utils/navigation/__init__.py
meyicloud_pw_ui_utils/navigation/navigation.py
meyicloud_pw_ui_utils/toasts/__init__.py
meyicloud_pw_ui_utils/toasts/toasts.py
meyicloud_pw_ui_utils/urls/__init__.py
meyicloud_pw_ui_utils/urls/urls.py
meyicloud_pw_ui_utils/utils/__init__.py
meyicloud_pw_ui_utils/utils/cards.py
meyicloud_pw_ui_utils/utils/dates.py
meyicloud_pw_ui_utils-1.0.0.dist-info/METADATA
meyicloud_pw_ui_utils-1.0.0.dist-info/WHEEL
meyicloud_pw_ui_utils-1.0.0.dist-info/top_level.txt
meyicloud_pw_ui_utils-1.0.0.dist-info/RECORD
