Metadata-Version: 2.4
Name: meyicloud-pw-ui-utils
Version: 1.0.0
Summary: Meyicloud private Playwright UI automation utilities
Author-email: Meyicloud Solutions <support@meyicloud.com>
License: MIT
Requires-Python: >=3.10
Requires-Dist: playwright>=1.41.0
Requires-Dist: pytest>=7.4.0
Requires-Dist: pytest-playwright>=0.3.0
